feature_store/README.md
feature_store/__init__.py
feature_store/app.py
feature_store/constants.py
feature_store/init_script.sh
feature_store/requirements.txt
feature_store/tsetsetes.py
feature_store/utils.py
feature_store_refract-1.0.27.dist-info/METADATA
feature_store_refract-1.0.27.dist-info/WHEEL
feature_store_refract-1.0.27.dist-info/top_level.txt
feature_store_refract-1.0.27.dist-info/RECORD
